apogee/__init__.py
apogee/align.py
apogee/apogee.py
apogee/apogee_main.py
apogee/create_genomes.py
apogee/rna_align.py
apogee/seq_utils.py
apogee/vcf_utils.py
RNA_APoGee-0.0.10.dist-info/LICENSE
RNA_APoGee-0.0.10.dist-info/METADATA
RNA_APoGee-0.0.10.dist-info/WHEEL
RNA_APoGee-0.0.10.dist-info/entry_points.txt
RNA_APoGee-0.0.10.dist-info/top_level.txt
RNA_APoGee-0.0.10.dist-info/RECORD
