Metadata-Version: 2.1
Name: RNA-APoGee
Version: 0.0.10
Summary: A package for aligning RNA-seq data without reference biases
Home-page: https://git.illumina.com/spanag/APoGee
Author: Sofia Panagiotopoulou
Author-email: spanagiotopoulou@gillumina.com
License: UNKNOWN
Platform: UNKNOWN
Classifier: Programming Language :: Python :: 3
Classifier: License :: OSI Approved :: GNU General Public License v3 (GPLv3)
Classifier: Operating System :: OS Independent
Requires-Python: >=3.6
Requires-Dist: numpy (>=1.16.4)
Requires-Dist: pandas (>=0.25.1)
Requires-Dist: pyfasta (>=0.5.2)
Requires-Dist: pysam (>=0.15.2)
Requires-Dist: PyVCF (>=0.6.8)
